drupal_news/__init__.py
drupal_news/ai_summarizer.py
drupal_news/cache_manager.py
drupal_news/cli.py
drupal_news/compile_scss.py
drupal_news/content_reader.py
drupal_news/data_cleaner.py
drupal_news/email_sender.py
drupal_news/index.py
drupal_news/metrics_collector.py
drupal_news/output_formatter.py
drupal_news/pipeline_integrity.py
drupal_news/process_logger.py
drupal_news/scheduler.py
drupal_news/validator.py
drupal_news/viewer.py
drupal_news/static/__init__.py
drupal_news/static/css/viewer.css
drupal_news/static/scss/README.md
drupal_news/static/scss/viewer.scss
drupal_news/utils/__init__.py
drupal_news/utils/config_loader.py
drupal_news/utils/consolidated_utils.py
drupal_news/utils/md_config_parser.py
drupal_news/utils/schema.py
drupal_news/utils/providers/__init__.py
drupal_news/utils/providers/anthropic_client.py
drupal_news/utils/providers/deepseek_client.py
drupal_news/utils/providers/gemini_client.py
drupal_news/utils/providers/generic_client.py
drupal_news/utils/providers/grok_client.py
drupal_news/utils/providers/lmstudio_client.py
drupal_news/utils/providers/ollama_client.py
drupal_news/utils/providers/openai_client.py
drupal_news/utils/providers/openrouter_client.py
drupal_news/utils/providers/qwen_client.py
drupal_news/utils/providers/unified_client.py
drupal_news-0.0.8.dist-info/licenses/LICENSE.txt
drupal_news-0.0.8.dist-info/METADATA
drupal_news-0.0.8.dist-info/WHEEL
drupal_news-0.0.8.dist-info/entry_points.txt
drupal_news-0.0.8.dist-info/top_level.txt
drupal_news-0.0.8.dist-info/RECORD
