Metadata-Version: 2.4
Name: drupal-news
Version: 0.0.8
Summary: Automated Drupal news aggregator with AI-powered summaries
Author: Drupal News Contributors
License: GPL-2.0
Project-URL: Homepage, https://github.com/theodorosploumis/drupal_news
Project-URL: Documentation, https://github.com/theodorosploumis/drupal_news#readme
Project-URL: Repository, https://github.com/theodorosploumis/drupal_news
Project-URL: Issues, https://github.com/theodorosploumis/drupal_news/issues
Project-URL: Changelog, https://github.com/theodorosploumis/drupal_news/blob/main/CHANGELOG.md
Keywords: drupal,news,aggregator,rss,ai,summarizer,newsletter
Classifier: Development Status :: 4 - Beta
Classifier: Intended Audience :: Developers
Classifier: Intended Audience :: System Administrators
Classifier: License :: OSI Approved :: GNU General Public License v2 (GPLv2)
Classifier: Operating System :: OS Independent
Classifier: Programming Language :: Python :: 3
Classifier: Programming Language :: Python :: 3.10
Classifier: Programming Language :: Python :: 3.11
Classifier: Programming Language :: Python :: 3.12
Classifier: Topic :: Communications :: Email
Classifier: Topic :: Internet :: WWW/HTTP :: Dynamic Content :: News/Diary
Classifier: Topic :: Software Development :: Libraries :: Python Modules
Classifier: Topic :: Text Processing :: Markup :: HTML
Requires-Python: >=3.10
License-File: LICENSE.txt
Requires-Dist: python-dotenv>=1.0
Requires-Dist: httpx>=0.27
Requires-Dist: feedparser>=6.0
Requires-Dist: lxml>=5.3
Requires-Dist: readability-lxml>=0.8
Requires-Dist: beautifulsoup4>=4.12
Requires-Dist: python-dateutil>=2.9
Requires-Dist: pytz>=2024.1
Requires-Dist: apscheduler>=3.10
Requires-Dist: jsonschema>=4.23
Requires-Dist: sqlite-utils>=3.36
Requires-Dist: loguru>=0.7
Requires-Dist: pyyaml>=6.0
Requires-Dist: flask>=3.0
Requires-Dist: markdown>=3.5
Requires-Dist: weasyprint>=66.0
Requires-Dist: libsass>=0.23
Requires-Dist: watchdog>=4.0
Provides-Extra: openai
Requires-Dist: openai>=1.45; extra == "openai"
Provides-Extra: anthropic
Requires-Dist: anthropic>=0.34; extra == "anthropic"
Provides-Extra: google
Requires-Dist: google-generativeai>=0.7; extra == "google"
Provides-Extra: qwen
Requires-Dist: dashscope>=1.17; extra == "qwen"
Provides-Extra: grok
Requires-Dist: xai-sdk>=0.3; extra == "grok"
Provides-Extra: deepseek
Requires-Dist: deepseek>=0.2; extra == "deepseek"
Provides-Extra: all-providers
Requires-Dist: openai>=1.45; extra == "all-providers"
Requires-Dist: anthropic>=0.34; extra == "all-providers"
Requires-Dist: google-generativeai>=0.7; extra == "all-providers"
Requires-Dist: dashscope>=1.17; extra == "all-providers"
Provides-Extra: dev
Requires-Dist: pytest>=8.3; extra == "dev"
Requires-Dist: pytest-cov>=4.1; extra == "dev"
Requires-Dist: black>=24.0; extra == "dev"
Requires-Dist: flake8>=7.0; extra == "dev"
Requires-Dist: mypy>=1.8; extra == "dev"
Requires-Dist: build>=1.0; extra == "dev"
Requires-Dist: twine>=5.0; extra == "dev"
Dynamic: license-file
